whitebox_workflows-1.3.5.dist-info/METADATA
whitebox_workflows-1.3.5.dist-info/WHEEL
whitebox_workflows-1.3.5.dist-info/licenses/LICENSE.txt
whitebox_workflows/py.typed
whitebox_workflows/__init__.py
whitebox_workflows/scripts/scripts.py
whitebox_workflows/scripts/__init__.py
whitebox_workflows/scripts/nibble.py
whitebox_workflows/scripts/utils.py
whitebox_workflows/scripts/burn_streams.py
whitebox_workflows/scripts/horton_ratios.py
whitebox_workflows/scripts/improved_ground_point_filter.py
whitebox_workflows/scripts/sieve.py
whitebox_workflows/scripts/ridge_and_valley_vectors.py
whitebox_workflows/whitebox_workflows.pyi
whitebox_workflows/whitebox_workflows.abi3.so
whitebox_workflows-1.3.5.dist-info/RECORD
