Metadata-Version: 2.4
Name: whitebox_workflows
Version: 1.3.5
Classifier: Programming Language :: Rust
Classifier: Programming Language :: Python :: Implementation :: CPython
Classifier: Programming Language :: Python :: Implementation :: PyPy
License-File: LICENSE.txt
Summary: whitebox_workflows is a Python library for advanced spatial analysis.
Keywords: spatial analysis,GIS,remote sensing
Author: Whitebox Geospatial Inc.
Author-email: support@whiteboxgeo.com
Requires-Python: >=3.8
